Workbook

Sheet VTR AGUARDANDO VISTORIA
A1: OS | B1: PLACA | C1: ANO | D1: MARCA/MODELO | E1: UNIDADE | F1: PREFIXO | G1: DATA DE ENTRADA NA LINHA | H1: TEMPO PARADA | I1: PROBLEMA RELATADO | J1: DATA DE SAÍDA | K1: DESTINO | L1: KM
A2: 17198 | B2: DMM7139 | D2: SPIN | E2: 16º BPM/M | F2: M-16330 | G2: 46027 | H2: 0 | I2: GRAFISMO | J2: 46027 | K2: GRAFISMO
A3: 18164 | B3: REV4E94 | C3: 2022 | D3: CHEV/S10 LT DD4A | E3: CMB | F3: 15-47 | G3: 46174 | H3: 0 | I3: • TROCA DOS QUATRO PNEUS 265/60R18. (REMANEJADOS). | J3: 46174 | K3: LIBERADO | L3: 68335
A4: 18244 | B4: CFY5823 | C4: 2013 | D4: TOYOTA/HILUX SW4 4X2SR | E4: APMTJ | F4: 3-145 | G4: 46188 | H4: 0 | I4: AVALIAÇÃO PARA CONTRATAÇÃO | J4: 46189 | K4: CONTRATAÇÃO | L4: 175283
A5: 17202 | B5: DJL9479 | D5: XRE300 | E5: 26ºBPMM | F5: M-26482 | G5: 46028 | H5: 1 | I5: SINALIZADOR | J5: 46029 | K5: SINALIZADOR
A6: 18405 | B6: FPI3C61 | C6: 2022 | D6: CHEV/TRAILBLAZER LT | E6: CAJ | F6: 1-28 | G6: 46219 | H6: 0 | I6: • AVALIAÇÃO. • AVALIAÇÃO.. • AVALIAÇÃO DEVOLUÇÃO SAF. • INJEÇÃO ELETRÔNICA - RESET VIA SCANNER. • INSPEÇÃO GERAL VTR - SEM NOVIDADES. • AVALIAÇÃO DEVOLUÇÃO SAF. • INJEÇÃO ELETRÔNICA - RESET VIA SCANNER. • INSPEÇÃO GERAL VTR - SEM NOVIDADES. | J6: 46220 | K6: LINHA MECÂNICA LIBERADO | L6: 219196
A7: 18163 | B7: REV4E91 | C7: 2022 | D7: CHEV/S10 LT DD4A | E7: DTIC | F7: 15-49 | G7: 46174 | H7: 0 | I7: . TROCA DE DOIS PNEUS 265/60R18 (REMANEJAMENTO) | J7: 46174 | K7: CONTRATAÇÃO | L7: 82203
A8: 17206 | B8: CKH2F73 | C8: 2021 | D8: TRAILBLAZER | E8: PMRG | F8: 17-461 | G8: 46028 | H8: 1 | I8: TROCA DE PASTILHAS FREIO DIANT. REVISÃO ELETRICA | J8: 46029 | K8: MECÂNICA
A9: 17208 | B9: BYQ7C54 | C9: 2022 | D9: TRAIBLAZER | E9: PMRG | F9: 17-462 | G9: 46028 | H9: 3 | I9: TROCA PASTILHAS FREIO DIANTEIRAS | J9: 46031 | K9: MECÂNICA
A10: 17209 | B10: FXS1E37 | D10: TRAIBLAZER | E10: EM PM | F10: 1-80 | G10: 46028 | H10: 0 | I10: SETOR TÉCNICO | J10: 46028 | K10: SETOR TÉCNICO
A11: 18084 | B11: SUF6A36 | C11: 2023 | D11: VW/17.230 OD | E11: CMM | F11: 7-47 | G11: 46163 | H11: 126 | I11: SOLDA DO ESCAPAMENTO | J11: 46188 | K11: LIBERADO | L11: 38911
A12: 17215 | B12: EXN4482 | D12: GOL | E12: 26º BPM/I | F12: I-26340 | G12: 46030 | H12: 53 | I12: PERÍCIA | J12: 46083 | K12: PERÍCIA
A13: 17216 | B13: EGI4246 | C13: 2020 | D13: SW4 | E13: CIPM | F13: 15-17 | G13: 46030 | H13: 0 | I13: BORRACHARIA | J13: 46030 | K13: BORRACHARIA
A14: 17217 | B14: GBG9B73 | D14: SPIN | E14: 34º BPM/I | F14: I-34105 | G14: 46030 | H14: 0 | I14: SINALIZADOR | J14: 46030 | K14: SINALIZADOR
A15: 17218 | B15: FUQ0566 | D15: SPIN | E15: 38º BPM/M | F15: 26-530 | G15: 46030 | H15: 5 | I15: SINALIZADOR | J15: 46035 | K15: SINALIZADOR
A16: 17219 | B16: CSP6C81 | C16: 2022 | D16: TRAILBLAZER | E16: GABCMTG | F16: 1-44 | G16: 46030 | H16: 0 | I16: MECÂNICA | J16: 46030 | K16: MECÂNICA
A17: 18387 | B17: CUE7E86 | C17: 2022 | D17: CHEV/TRAILBLAZER LT | E17: CMT GERAL | F17: 15-74 | G17: 46217 | H17: 4 | I17: • TROCA DE DOIS PNEUS 265/60/18. • ALINHAMENTO DE DIREÇÃO. • BALANCEAMENTO DE RODAS. | J17: 46219 | K17: BORRACHARIA LIBERADO | L17: 69087
A18: 17221 | B18: CFY5F18 | D18: HILUX | E18: EEF | F18: 3-325 | G18: 46030 | H18: 0 | I18: VIATURA NÃO FUNCIONA (MOTOR) | J18: 46030 | K18: MECÂNICA/SINAL
A19: 18413 | B19: CJJ7F93 | C19: 2022 | D19: CHEV/TRAILBLAZER LT | E19: APMTJ | F19: 1-61 | G19: 46220 | H19: 0 | I19: • AVALIAÇÃO PARA CONTRATAÇÃO. • REVISÃO DOS 100 MIL/KM. | J19: 46223 | K19: LINHA MECÂNICA CONTRATAÇÃO | L19: 98306
A20: 17223 | B20: FEQ9H11 | D20: TRAILBLAZER | E20: 25º BPM/M | F20: M-25171 | G20: 46030 | H20: 0 | I20: SINALIZADOR | J20: 46030 | K20: SINALIZADOR
A21: 17225 | B21: GGO3962 | C21: 2018 | D21: TRAILBLAZER | E21: EEF | F21: EEF-004 | G21: 46030 | H21: 6 | I21: TROCA DE BATERIA E AS 3 PALHETAS | J21: 46036 | K21: MECÂNICA
A22: 17227 | B22: GFO7I66 | C22: 2022 | D22: TRAILBLAZER | E22: SAF | F22: 15-298 | G22: 46030 | H22: 4 | I22: TROCA BATERIA (REVISÃO FREIOS, FLUIDOS E FILTROS, OK) | J22: 46034 | K22: MECÂNICA
A23: 17229 | B23: EEF9580 | C23: 2014 | D23: COROLLA | E23: SENASP | F23: 15-241 | G23: 46030 | H23: 0 | I23: TROCA DE BATERIA | J23: 46030 | K23: MECÂNICA
A24: 17231 | B24: DJM8692 | C24: 2014 | D24: CRUZE | E24: CMED | F24: 15-114 | G24: 46030 | H24: 126 | I24: BATERIA, ARREFECIMENTO | K24: MECÂNICA
A25: 18061 | B25: EDI2I97 | C25: 2021 | D25: RENAULT/MASTER L2H2 MNPA | E25: C MED | F25: 5-24 | G25: 46161 | H25: 4 | I25: • CARGA NA BATERIA. • MUDANÇA DA INSTALAÇÃO DO RADIO OPERACIONAL NA BATERIA AUXILIAR. | J25: 46164 | K25: LIBERADO | L25: 20505
A26: 17233 | B26: EEF8705 | C26: 2014 | D26: S-10 | E26: CMB | F26: 3-59 | G26: 46030 | H26: 1 | I26: TROCA DE BATERIA E REVISÃO ELÉTRICA | J26: 46031 | K26: MECÂNICA/SINAL
A27: 17234 | B27: DFL7906 | D27: XRE300 | E27: 39ºBPMM | F27: M-39380 | G27: 46031 | H27: 125 | I27: GRAFISMO | K27: GRAFISMO
A28: 17235 | B28: DJL9246 | D28: XRE300 | E28: 39ºBPMM | F28: M-39381 | G28: 46031 | H28: 0 | I28: GRAFISMO | J28: 46031 | K28: GRAFISMO
A29: 17237 | B29: FRU3184 | C29: 2015 | D29: SPIN | E29: DL | F29: 22-523 | G29: 46031 | H29: 6 | I29: REAPERTO TERMINAL BATERIA | J29: 46037 | K29: MECÂNICA
A30: 17239 | B30: BOT5I18 | D30: LANDER | E30: CMM | F30: 19-2 | G30: 46034 | H30: 3 | I30: MECÂNICA | J30: 46037 | K30: MECÂNICA
A31: 17240 | B31: DJL1175 | D31: GOL | E31: DEC | F31: 15-209 | G31: 46034 | H31: 0 | I31: BORRACHARIA | J31: 46034 | K31: BORRACHARIA
A32: 18316 | B32: FPF0B04 | C32: 2022 | D32: CHEV/TRAILBLAZER LT | E32: EM/PM | F32: 1-81 | G32: 46198 | H32: 0 | I32: . TROCA DA LAMPADA H7 | J32: 46204 | K32: LINHA MECÂNICA LIBERADO | L32: 41538
A33: 17242 | B33: GCP4F05 | C33: 2022 | D33: TRAILBLAZER | E33: SAF | F33: 1-84 | G33: 46034 | H33: 0 | I33: TROCA DO PARA-BRISA COM GUARNIÇÃO, APLICAÇÃO DE PELÍCULA INSULFILM NO PARA-BRISA, TROCA DAS LAMPADAS DE MEIA-LUZ E LANTERNA TRAZEIRA (LED). | J33: 46034 | K33: MECÂNICA
A34: 18057 | B34: FNA3823 | C34: 2017 | D34: CHEV/SPIN 1.8L MT LT | E34: COPOM | F34: 22-296 | G34: 46160 | H34: 21 | I34: REPAROS NO CHICOTE E TROCA DE RELE AUXILIAR | J34: 46160 | K34: LIBERADO | L34: 95254
A35: 17244 | B35: EEF8992 | C35: 2014 | D35: SPACEFOX | E35: COPOM | F35: 22-69 | G35: 46034 | H35: 24 | I35: BATERIA, SENSOR DO ACELERADOR. | J35: 46058 | K35: MECÂNICA
A36: 17245 | B36: EEF9606 | C36: 2014 | D36: COROLLA | E36: SAF | F36: 1-168 | G36: 46034 | H36: 0 | I36: TROCA PARA-BARROS LD E LE, LENTES FAROIS DE NEBLINA, MAÇANETA PORTA TRAZ LD | J36: 46034 | K36: MECÂNICA
A37: 17246 | B37: FTI7A82 | D37: DUSTER | E37: 50ºBPMI | F37: I-50248 | G37: 46035 | H37: 0 | I37: SINALIZADOR | J37: 46035 | K37: SINALIZADOR
A38: 17247 | B38: EYK7132 | D38: SPIN | E38: 47ºBPMI | F38: I-47616 | G38: 46035 | H38: 45 | I38: SETOR TÉCNICO | J38: 46080 | K38: SETOR TÉCNICO
A39: 17248 | B39: FQB5482 | C39: 2015 | D39: COBALT | E39: APMAL | F39: 15-203 | G39: 46035 | H39: 0 | I39: CONTRATAÇÃO CONFORME OFÍCIO | J39: 46035 | K39: MECÂNICA
A40: 17249 | B40: GCI9C06 | D40: TRAILBLAZER | E40: 13º BPM/M | F40: M-13019 | G40: 46035 | H40: 0 | I40: GRAFISMO | J40: 46035 | K40: GRAFISMO
A41: 17252 | B41: GJT3D63 | C41: 2022 | D41: TRAILBLAZER | E41: SAF | F41: 15-299 | G41: 46035 | H41: 121 | I41: REISADA | K41: MECÂNICA
A42: 17253 | B42: EDI3478 | C42: 2018 | D42: SPIN | E42: MUSEU PM | F42: 15-236 | G42: 46036 | H42: 0 | I42: TROCA DO ESCAPAMENTO COMPLETO (REMANEJADO), TESTE DE BATERIA, ALTERNADOR E MOTOR DE ARRANQUE | J42: 46036 | K42: MECÂNICA
A43: 17255 | B43: FRP1496 | D43: SPIN | E43: DSACG | F43: 22-801 | G43: 46036 | H43: 13 | I43: RECARGA NA BATERIA, REPARO NO CHICOTE DA COLUNA ELÉTRICA DE DIREÇÃO | J43: 46049 | K43: MECÂNICA
A44: 17257 | B44: GBC8430 | C44: 2015 | D44: SPIN | E44: DSACG | F44: 22-979 | G44: 46036 | H44: 16 | I44: CONSTATADO QUEBRA PRECOCE DO BRAÇO DA SUSPENSÃO LADO DIREITO, OCASIONANDO BARULHO NA SUSPENSÃO, VTR ENCAMINHADA PARA O SETOR TÉCNICO PARA APURAÇÃO DE POSSÍVEL RESPONSABILIDADE DE CAUSA | J44: 46052 | K44: MECÂNICA
A45: 002/26 | B45: FGV1B53 | D45: CACTUS | E45: APMSSP | F45: S/PREFIXO | G45: 46037 | H45: 0 | I45: BORRACHARIA | J45: 46037 | K45: BORRACHARIA
A46: 18221 | B46: CUJ9C77 | C46: 2022 | D46: GM /TRAILBLAZER | E46: DPCDH | F46: 1-48 | G46: 46183 | H46: 0 | I46: EM EXECUÇÃO TROCA DOS DISCOS DE FREIO DIANTEIRO • PASTILHAS DE FREIO - DIANTEIRAS E TRASEIRAS • FLUÍDO DE FREIO DOT-4 TROCA DOS DISCOS DE FREIO DIANTEIRO • PASTILHAS DE FREIO - DIANTEIRAS E TRASEIRAS • FLUÍDO DE FREIO DOT-4 | J46: 46199 | K46: LIBERADO | L46: 156608
A47: 18169 | B47: EXL5G73 | C47: 2022 | D47: CHEV/SPIN 18L AT PREMIER | E47: APMTJ | F47: 22-127 | G47: 46174 | H47: 5 | I47: DOCUMENTOS AO SETOR | K47: EM ATENDIMENTO | L47: 58756
A48: 17976 | B48: EEF9594 | C48: 2014 | D48: TOYOTA/COROLLA XEI20FLEX | E48: CMM | F48: 15-274 | G48: 46148 | H48: 5 | I48: • REPARO DAS PINÇAS DE FEIO DIANTEIRAS. | J48: 46162 | K48: LIBERADO | L48: 147597
A49: 17260 | B49: GIX7J12 | D49: RANGER | E49: 1ºBPTRAN | F49: T-01006 | G49: 46037 | H49: 0 | I49: SINALIZADOR | J49: 46037 | K49: SINALIZADOR
A50: 17261 | B50: DBM7437 | C50: 2019 | D50: GOL | E50: DPCDH | F50: 22-958 | G50: 46037 | H50: 6 | I50: TROCA DA BATERIA E REPROGRAMAÇÃO DO ALARME | J50: 46043 | K50: MECÂNICA
A51: 17263 | B51: FPP0711 | D51: TRAILBLAZER | E51: 15ºBAEP | F51: E-15107 | G51: 46037 | H51: 0 | I51: BORRACHARIA | J51: 46037 | K51: BORRACHARIA
A52: 17264 | B52: DFL0941 | D52: XRE 300 | E52: 13º BPM/M | F52: 19-312 | G52: 46037 | H52: 119 | I52: SINALIZADOR | K52: SINALIZADOR
A53: 17267 | B53: CUH0708 | C53: 2019 | D53: GOL | E53: CIPM | F53: 8-347 | G53: 46037 | H53: 7 | I53: PASTILHAS DE FREIO, CORREIA DENTADA, TENSOR DA CORREIA DENTADA, CORREIA DE SERVIÇO, VELAS DE IGNIÇÃO, CABOS DAS VELAS, LÂMAPADA DO FAROL DE MILHA ESQUERDO, LÂMPADA DA LUZ DE PLACA, LIMPEZA DOS BICOS INJETORES, LIMPEZA DO TBI . | J53: 46044 | K53: MECÂNICA
A54: 17269 | B54: FSK7861 | C54: 2017 | D54: SPIN | E54: DSA/CG | F54: 22-892 | G54: 46037 | H54: 119 | I54: AVALIADO SISTEMA DE ARREFECIMENTO, CONSTATADO QUEIMA DA JUNTA DO CABEÇOTE POR SUPERAQUECIMENTO, VTR ENCAMINHADA PARA O SETOR TÉCNICO PARA APURAÇÃO DE POSSÍVEL RESPONSABILIDADE | K54: MECÂNICA
A55: 003/26 | B55: FPO8J31 | C55: 2023 | D55: C.CROSS | E55: APMTJ | F55: 22-110 | G55: 46038 | H55: 3 | I55: RECARGA DE BATERIA | J55: 46041 | K55: MECÂNICA
A56: 17271 | B56: DKK4127 | C56: 2018 | D56: SPIN | E56: DL | F56: 22-121 | G56: 46038 | H56: 118 | I56: REVISÃO SUSPENSÃO, BATERIA, ALTERNADOR, LIQUIDO ARREFECIMENTO BAIXANDO. | K56: MECÂNICA
A57: 17272 | B57: FPF0B04 | C57: 2022 | D57: TRAILBLAZER | E57: EM PM | F57: 1-81 | G57: 46038 | H57: 118 | I57: BORRACHARIA | K57: BORRACHARIA
A58: 18137 | B58: FXK8J56 | C58: 2022 | D58: GM/TRAILBLAZER | E58: CPI-6 | F58: E-02102 | G58: 46170 | H58: 118 | I58: TROCA DE SINALIZADORES | J58: 46170 | K58: LIBERADO | L58: 53447
A59: 17274 | B59: CJJ7F93 | C59: 2022 | D59: TRAILBLAZER | E59: APMTJ | F59: 1-61 | G59: 46038 | H59: 118 | I59: TROCA LAMPADA LUZ DE CIDADE LE, LAMPADA DE PLACA LE, PALHETAS LIMPADOR DE PARA-BRISA | K59: MECÂNICA
A60: 17275 | B60: REV4E94 | C60: 2022 | D60: S-10 | E60: CMB | F60: 15-47 | G60: 46041 | H60: 1 | I60: PASTILHAS DE FREIO, REGULAGEM NO FREIO DE ESTACION AMENTO, REPARO NOS FEIXE DE MOLA, REAPERTO E LUBRIFICAÇÃO NA SUSPEN~SAO DAINBTEIRA E REAPERTO NO BANCO DO PASSAGEIRO | J60: 46042 | K60: MECÂNICA
A61: 17276 | B61: GHK0550 | D61: XT660 | E61: 2ºBPTRAN | F61: T-02219-11 | G61: 46041 | H61: 115 | I61: SINALIZADOR | K61: SINALIZADOR
A62: 17277 | B62: DAT0J94 | D62: TRAILBLAZER | E62: 13ºBPMM | F62: M-13015 | G62: 46041 | H62: 115 | I62: SINALIZADOR | K62: SINALIZADOR
A63: 17279 | B63: FYV8G25 | D63: TRAILBLAZER | E63: 12º BPM/I | F63: I-12013 | G63: 46042 | H63: 0 | I63: SINALIZADOR | J63: 46042 | K63: SINALIZADOR
A64: 17281 | B64: BYP0J41 | D64: TRAILBLAZER | E64: 7º BAEP | F64: E-07221 | G64: 46042 | H64: 0 | I64: BORRACHARIA | J64: 46042 | K64: BORRACHARIA
A65: 17282 | B65: GGR8B15 | C65: 2022 | D65: TRAILBLAZER | E65: CCOMSOC | F65: 3-186 | G65: 46042 | H65: 0 | I65: TROCA DAS PASTILHAS DE FREIO DIANTEIRO E TRASEIRO, TROCA DOS DISCOS DE FREIO DIANTEIRO | J65: 46042 | K65: MECÂNICA
A66: 17283 | B66: DJM8728 | C66: 2014 | D66: FIORINO | E66: CIPM | F66: 8-334 | G66: 46042 | H66: 3 | I66: BOBINA ( REMANEJADA) PNEUS E LANTERNA TRASEIRA DIREITA ( REMANEJADA) | J66: 46045 | K66: MECÂNICA
A67: 17285 | B67: GEU9219 | D67: S-10 | E67: 2º BPTRAN | F67: T-02153 | G67: 46042 | H67: 3 | I67: SINALIZADOR | J67: 46045 | K67: SINALIZADOR
A68: 17287 | B68: ESE7016 | D68: HD | E68: CMM | F68: 14-52 | G68: 46042 | H68: 114 | I68: MECÂNICA | K68: MECÂNICA
A69: 17288 | B69: FPT9F57 | C69: 2022 | D69: TRAILBLAZER | E69: ESSD | F69: 1-45 | G69: 46042 | H69: 0 | I69: TROCA DE BATERIA E LAMPADA DE 1 POLO (FREIO) | J69: 46042 | K69: MECÂNICA
A70: 17289 | B70: FIP0I47 | C70: 2022 | D70: TRAILBLAZER | E70: CIPM | F70: 1-49 | G70: 46042 | H70: 114 | I70: REVISÃO NOS FREIOS, TROCA DE FLUIDO DE FREIO, TROCA DOS AMORT DIANT E TRAS COM BATENTES E BUCHAS, TROCA DO FILTRO DE AR DA CABINE E HIGIENIZAÇÃO, TROCA DO ÓLEO DO MOTOR, REVISÃO NO SIST DE ILUMINAÇÃO, CONTRATAÇÃO DE SERVIÇOS. | K70: MECÂNICA
A71: 17290 | B71: BVT6566 | D71: SPIN | E71: 22º BPM/M | F71: M-22225 | G71: 46043 | H71: 113 | I71: BORRACHARIA | K71: BORRACHARIA
A72: 18058 | B72: FXL0F73 | C72: 2023 | D72: CHEV/TRAILBLAZER LT | E72: GAB CMT G | F72: 1-2 | G72: 46160 | H72: 113 | I72: TROCA DO ÓLEO DE TRANSMISSÃO. | K72: EM ATENDIMENTO | L72: 36971
A73: 17293 | B73: FNE8D96 | D73: GOL | E73: 38º BPM/M | F73: M-38113 | G73: 46043 | H73: 113 | I73: SINALIZADOR | K73: SINALIZADOR
A74: 17294 | B74: DJM8130 | C74: 2014 | D74: HILUX SW4 | E74: 38ºBPMM | F74: 3-158 | G74: 46043 | H74: 113 | I74: TROCA DOS AMORTECEDORES TRAZEIROS (TROUXERAM OS AORTECEDORES) | K74: MECÂNICA
A75: 17295 | B75: BSY1D71 | C75: 2022 | D75: SPIN | E75: APMTJ | F75: 17-75 | G75: 46043 | H75: 113 | I75: TROCA DA BATERIA, LAMPADA H4 LE, 2X LAMPADA PINGÃO TRAZ. | K75: MECÂNICA
A76: 17306 | B76: CMW7395 | C76: 2011 | D76: VECTRA | E76: COORD OP PM | F76: 15-150 | G76: 46044 | H76: =IF(G76="","",IF(J76="",TODAY()-G76,J76-G76)) -> 40 | I76: AGUARDARDANDO DETERMINAÇÃO SUPERIOR | J76: 46084
A77: 16:16 | B77: DLF0478 | D77: XRE 300 | E77: 10º BPM/M | F77: M-10382 | G77: 46044 | H77: 11 | I77: SINALIZADOR | J77: 46055 | K77: SINALIZADOR
A78: 17297 | B78: EEF9093 | C78: 2015 | D78: GOL | E78: CIPM | F78: 8-364 | G78: 46044 | H78: 0 | I78: TROCA DA LÂMPADA DO FAROL BAIXO L.D., LÂMPADA DA LANTERNA DIANT. L.E., LÂMPAFDA LANTERNA TRAS. L.D. | J78: 46044 | K78: BORRACHARIA
A79: 18098 | B79: EPA2765 | C79: 2019 | D79: CHEV/SPIN 1.8L MT LT | E79: CMM | F79: 22-375 | G79: 46164 | H79: 0 | I79: • ANALISE DO MOTOR DE ARRANQUE, EFETUADO CARGA NA BATERIA, COLOCADO BATERIA NOVA, ENCAMINHADO PARA BORRACHARIA TROCA DE PNEUS DIANTEIROS | J79: 46177 | K79: BORRACHARIA | L79: 155741
A80: 17299 | B80: EZP6J36 | D80: SPIN | E80: 36º BPM/M | F80: M-36400 | G80: 46044 | H80: 112 | I80: MECÂNICA | K80: MECÂNICA
A81: 17300 | B81: CMW7378 | C81: 2010 | D81: VECTRA | E81: SAF | F81: 15-140 | G81: 46044 | H81: 11 | I81: REVISÃO DE DEVOLUÇÃO, SUSPENSÃO ESQUERDA | J81: 46055 | K81: MECÂNICA
A82: 17302 | B82: CMW8260 | C82: 2011 | D82: VECTRA | E82: SAF | F82: 15-194 | G82: 46044 | H82: 112 | I82: CONTRATAÇÃO | K82: MECÂNICA
A83: 17305 | B83: DJM8693 | C83: 2014 | D83: CRUZE | E83: DTIC | F83: 8-50 | G83: 46044 | H83: 112 | I83: VTR NÃO LIGA, ARREFECIMENTO | K83: MECÂNICA
A84: 17306 | B84: CMW7395 | C84: 2011 | D84: VECTRA | E84: COORDOP | F84: 15-50 | G84: 46044 | H84: 0 | I84: BATERIA, UNIDADE NÃO QUER A VTR | J84: 46044 | K84: MECÂNICA
A85: 004/26 | B85: SSN5B73 | C85: 2025 | D85: YARIS | E85: CAPS | F85: 15-338 | G85: 46045 | H85: 10 | I85: MECANICA | J85: 46055 | K85: MECANICA
A86: 17307 | B86: FPK6J63 | D86: SPIN | E86: 37ºBPMM | F86: M-37330 | G86: 46045 | H86: 0 | I86: SETOR TÉCNICO | J86: 46045 | K86: SETOR TÉCNICO
A87: 17309 | B87: DAM9373 | C87: 2018 | D87: SPIN | E87: COORD OP PM | F87: 22-726 | G87: 46045 | H87: 7 | I87: TROCADO BATERIA NOVA | J87: 46052 | K87: MECÂNICA
A88: 18267 | B88: FNX4A94 | C88: 2022 | D88: CHEV/TRAILBLAZER LT | E88: DP | F88: 1-47 | G88: 46191 | H88: 111 | I88: . REVISÃO ELÉTRICA . TROCA DO RELÉ (ARPE RA1012-150A) • TROCA LÂMPADA DE PLACA • TROCA LÂMPADA DE FREIO | J88: 46204 | K88: LIBERADO | L88: 114346
A89: 17788 | B89: CFY5G42 | C89: 2013 | D89: TOYOTA/HILUX SW4 4X2SR | E89: DL | F89: 3-438 | G89: 46113 | H89: 111 | I89: • REAPARO PNEU. | J89: 46219 | K89: LINHA MECÂNICA LIBERADO | L89: 80141
A90: 17313 | B90: DJP1232 | D90: ONIBUS | E90: EEF | F90: 7-44 | G90: 46045 | H90: 111 | I90: MECÂNICA | K90: MECÂNICA
A91: 17315 | B91: EEF9093 | C91: 2015 | D91: GOL | E91: CIPM | F91: 8-364 | G91: 46048 | H91: 108 | I91: BORRACHARIA | K91: BORRACHARIA
A92: 17316 | B92: FKP4B86 | D92: SPIN | E92: CPAM-6 | F92: M-24139 | G92: 46048 | H92: 108 | I92: SETOR TÉCNICO | K92: SETOR TÉCNICO
A93: 17317 | B93: CUE7E86 | C93: 2022 | D93: TRAILBLAZER | E93: CMT GERAL | F93: 15-74 | G93: 46048 | H93: 1 | I93: TROCA PASTILHAS DE FREIO DIANTEIRAS E TRAZEIRAS, REGULAGEM FREIO DE ESTACIONAMENTO | J93: 46049 | K93: MECÂNICA
A94: 17318 | B94: FEE9416 | D94: TRAILBLAZER | E94: 1º BPTRAN | F94: T-01230 | G94: 46048 | H94: 3 | I94: SINALIZADOR | J94: 46051 | K94: SINALIZADOR
A95: 17320 | B95: CEN0F64 | C95: 2022 | D95: TRAILBLAZER | E95: APMPMSP | F95: 1-55 | G95: 46048 | H95: 108 | I95: TROCA DA BATERIA PRINCIPAL, REVISÃO ELÉTRICA | K95: MECÂNICA
A96: 17321 | B96: EVU9I84 | D96: MASTER | E96: CMED | F96: 5-20 | G96: 46048 | H96: 108 | I96: MECÂNICA | K96: MECÂNICA
A97: 17322 | B97: EXG5625 | C97: 2019 | D97: SIENA | E97: GAB CMT GERAL | F97: 15-195 | G97: 46048 | H97: 108 | I97: TROCA LAMPADAS | K97: BORRACHARIA
A98: 005/26 | B98: FPO8J31 | C98: 2023 | D98: C.CROSS | E98: APMTJ | F98: 22-110 | G98: 46049 | H98: 0 | I98: ELABORADO CHECK-LIST PARA CONTRATAÇÃO | J98: 46049 | K98: MECÂNICA
A99: 006/26 | B99: SVL1C19 | C99: 2023 | D99: C.CROSS | E99: CMIL | F99: 22-88 | G99: 46049 | H99: 29 | I99: ELABORADO CHECK-LIST PARA CONTRATAÇÃO | J99: 46078 | K99: MECÂNICA
A100: 17324 | B100: EYN7B54 | C100: 2022 | D100: CRUZE | E100: CIPM | F100: 8-411 | G100: 46049 | H100: 30 | I100: TROCA ÓLEO DE CAMBIO | J100: 46079 | K100: MECÂNICA
...

Sheet VTR DESCARGA
A1: OS | B1: PLACA | C1: ANO | D1: MARCA/MODELO | E1: UNIDADE | F1: Prefixo | G1: DATA DE ENTRADA NA LINHA | H1: TEMPO PARADA | I1: PROBLEMA RELATADO | J1: DATA DE SAÍDA | K1: DESTINO
A2: 10712 | B2: DJL2441 | C2: 2012 | D2: PALIO WEEK | E2: DPCDH | F2: 22-337 | G2: 45271 | H2: =IF(G2="","",IF(J2="",TODAY()-G2,J2-G2)) -> 182 | I2: ESCAPAMENTO/CAIXA E BOMBA DE DIREÇÃO/PNEUS | J2: 45453 | K2: CONTRATAÇÃO - DESCARGA
A3: 11547 | B3: EEF4106 | C3: 2009 | D3: ASTRA | E3: CMM | F3: 22-330 | G3: 45344 | H3: =IF(G3="","",IF(J3="",TODAY()-G3,J3-G3)) -> 110 | I3: VAZAMENTO COMB/ MOTOR Ñ FUNCIONA/ CHEIRO EMBR. CAMBIO/ COXINS AMORTECEDORES/ VERIFICAR CORREIAS/ AR INOPERANTE | J3: 45454 | K3: CONTRATAÇÃO - DESCARGA
A4: 11840 | B4: GBO4311 | C4: 2017 | D4: SPIN | E4: APMTJ | F4: 22-89 | G4: 45359 | H4: =IF(G4="","",IF(J4="",TODAY()-G4,J4-G4)) -> 95 | I4: CONSUMO ÓLEO / BARULHO NA SUSPENSÃO | J4: 45454 | K4: CONTRATAÇÃO - DESCARGA
A5: 11680 | B5: CFY5839 | C5: 2014 | D5: TRAILBLAZER | E5: DTIC | F5: 3-424 | G5: 45352 | H5: =IF(G5="","",IF(J5="",TODAY()-G5,J5-G5)) -> 104 | I5: SUSPENSÃO/ FREIO/ CAMBIO | J5: 45456 | K5: CONTRATAÇÃO - DESCARGA
A6: 11273 | B6: DJL0953 | C6: 2008 | D6: KOMBI | E6: CAVPM | F6: 3-168 | G6: 45321 | H6: =IF(G6="","",IF(J6="",TODAY()-G6,J6-G6)) -> 136 | I6: CAMBIO/ MOTOR/ SUSPENSÃO | J6: 45457 | K6: CONTRATAÇÃO - DESCARGA
A7: 11908 | B7: CFY5799 | C7: 2013 | D7: HILUX | E7: ESSD | F7: 3-37 | G7: 45363 | H7: =IF(G7="","",IF(J7="",TODAY()-G7,J7-G7)) -> 97 | I7: SUSPENSÃO/ FREIO/ MOTOR/ CAMBIO | J7: 45460 | K7: CONTRATAÇÃO - DESCARGA
A8: 11906 | B8: FXR6994 | C8: 2017 | D8: PALIO WEEK | E8: ESSD | F8: 22-315 | G8: 45363 | H8: =IF(G8="","",IF(J8="",TODAY()-G8,J8-G8)) -> 97 | I8: SUSPENSÃO/ FREIO/ MOTOR/ CAMBIO | J8: 45460 | K8: CONTRATAÇÃO - DESCARGA
A9: 11595 | B9: DJL6019 | C9: 2011 | D9: BLAZER | E9: CMM | F9: 15-16 | G9: 45348 | H9: =IF(G9="","",IF(J9="",TODAY()-G9,J9-G9)) -> 113 | I9: ELÉTRICO ( VTR ENCHENTE DO CMM ) | J9: 45461 | K9: CONTRATAÇÃO - DESCARGA
A10: 12999 | B10: FJH5857 | C10: 2017 | D10: PALIO WEEK | E10: CMM | F10: 22-1092 | G10: 45453 | H10: =IF(G10="","",IF(J10="",TODAY()-G10,J10-G10)) -> 8 | I10: LUZ ANOMALIA ACESA ( BAIXA PRESSÃO DE ÓLEO ) | J10: 45461 | K10: CONTRATAÇÃO - DESCARGA
A11: 11574 | B11: DJM0137 | C11: 2011 | D11: PARATI | E11: CMM | F11: 22-631 | G11: 45344 | H11: =IF(G11="","",IF(J11="",TODAY()-G11,J11-G11)) -> 295 | I11: REVISÃO GERAL | J11: 45639 | K11: CONTRATAÇÃO - DESCARGA
A12: 12454 | B12: GAT6417 | C12: 2018 | D12: SPIN | E12: EEF | F12: 22-1184 | G12: 45404 | H12: =IF(G12="","",IF(J12="",TODAY()-G12,J12-G12)) -> 235 | I12: CAMBIO NÃO ENGATA 3º MARCHA | J12: 45639 | K12: CONTRATAÇÃO - DESCARGA
A13: 12492 | B13: GAC3646 | C13: 2015 | D13: SPIN | E13: DEC | F13: 22-382 | G13: 45406 | H13: =IF(G13="","",IF(J13="",TODAY()-G13,J13-G13)) -> 233 | I13: CHAVE QUEBRADA/ PAINEL DEFEITUOSO/ ARREFECIMENTO/ PANE ELÉTRICA | J13: 45639 | K13: CONTRATAÇÃO - DESCARGA
A14: 202/24 | B14: FCF9549 | C14: 2017 | D14: PALIO WEEK | E14: DF/CIAP | F14: 22-1308 | G14: 45489 | H14: =IF(G14="","",IF(J14="",TODAY()-G14,J14-G14)) -> 150 | I14: BATERIA/ PANE ELETRICA/ MOTOR RAJANDO | J14: 45639 | K14: CONTRATAÇÃO - DESCARGA
A15: 13788 | B15: EEF5753 | C15: 2010 | D15: PARATI | E15: CAPS | F15: 15-351 | G15: 45534 | H15: =IF(G15="","",IF(J15="",TODAY()-G15,J15-G15)) -> 47 | I15: SUSPENSÃO. MOTOR , FREIO | J15: 45581 | K15: CONTRATAÇÃO - DESCARGA
A16: 14-477 | B16: FOF9372 | C16: 2017 | D16: SPIN | E16: CMM-SAF | F16: 22-336 | G16: 45628 | H16: =IF(G16="","",IF(J16="",TODAY()-G16,J16-G16)) -> 80 | I16: DIREÇÃO ELÉTRICA, PAINEL. PANE ELETRICA | J16: 45708 | K16: CONTRATAÇÃO - DESCARGA
A17: 14465 | B17: EEF9238 | C17: 2014 | D17: SPACEFOX | E17: CMM/SAF | F17: 22-1306 | G17: 45624 | H17: =IF(G17="","",IF(J17="",TODAY()-G17,J17-G17)) -> 89 | I17: POSSÍVEL DESCARGA | J17: 45713 | K17: CONTRATAÇÃO - DESCARGA
A18: 14825 | B18: GBA6310 | C18: 2015 | D18: SPIN | E18: APMBB | F18: BA-046 | G18: 45681 | H18: =IF(G18="","",IF(J18="",TODAY()-G18,J18-G18)) -> 69 | I18: MOTOR QUEIMANDO ÓLEO | J18: 45750 | K18: CONTRATAÇÃO - DESCARGA
A19: 15423 | B19: GBZ0400 | C19: 2015 | D19: SPIN | E19: ESSD | F19: ESSD-057 | G19: 45747 | H19: =IF(G19="","",IF(J19="",TODAY()-G19,J19-G19)) -> 43 | I19: REVISÃO GERAL | J19: 45790 | K19: CONTRATAÇÃO - DESCARGA
A20: 15464 | B20: EEF5758 | C20: 2010 | D20: PARATI | E20: CMM - SAF | F20: 22-731 | G20: 45750 | H20: =IF(G20="","",IF(J20="",TODAY()-G20,J20-G20)) -> 53 | I20: AVALIAÇÃO DE RECOLHA | J20: 45803 | K20: CONTRATAÇÃO - DESCARGA
A21: 15744 | B21: FWP1363 | C21: 2018 | D21: SPIN | E21: CPC | F21: 22-824 | G21: 45785 | H21: =IF(G21="","",IF(J21="",TODAY()-G21,J21-G21)) -> 46 | I21: FALHA MOTOR | J21: 45831 | K21: CONTRATAÇÃO - DESCARGA
A22: 15749 | B22: CMW7425 | C22: 2010 | D22: VECTRA | E22: C MED | F22: 15-131 | G22: 45785 | H22: =IF(G22="","",IF(J22="",TODAY()-G22,J22-G22)) -> 46 | I22: REVISÃO GERAL, PNEUS, MOTOR, FREIO | J22: 45831 | K22: CONTRATAÇÃO - DESCARGA
A23: 15762 | B23: CMW7379 | C23: 2010 | D23: VECTRA | E23: SAF | F23: 15-124 | G23: 45786 | H23: =IF(G23="","",IF(J23="",TODAY()-G23,J23-G23)) -> 94 | I23: MOTOR/SUSPENSÃO/DERIVADOS | J23: 45880 | K23: CONTRATAÇÃO - DESCARGA
A24: 16193 | B24: CDV3430 | C24: 2002 | D24: KOMBI | E24: C ODONT | F24: 3-1081 | G24: 45852 | H24: =IF(G24="","",IF(J24="",TODAY()-G24,J24-G24)) -> 28 | I24: CAMBIO / SUSPENSÃO / PNEUS | J24: 45880 | K24: CONTRATAÇÃO - DESCARGA
A25: 16295 | B25: CMW7432 | C25: 2010 | D25: VECTRA | E25: CAJ PM | F25: 15-191 | G25: 45868 | H25: =IF(G25="","",IF(J25="",TODAY()-G25,J25-G25)) -> 13 | I25: REVISÃO GERAL. | J25: 45881 | K25: CONTRATAÇÃO - DESCARGA
A26: 16399 | B26: CMW7426 | C26: 2010 | D26: VECTRA | E26: C COM SOC | F26: 15-164 | G26: 45882 | H26: =IF(G26="","",IF(J26="",TODAY()-G26,J26-G26)) -> 2 | I26: ESCAPAMENTO, SUSPENSÃO. REVISÃO GERAL. | J26: 45884 | K26: CONTRATAÇÃO - DESCARGA
A27: 16188 | B27: CMW7386 | C27: 2010 | D27: VECTRA | E27: C COM SOC | F27: 15-146 | G27: 45849 | H27: =IF(G27="","",IF(J27="",TODAY()-G27,J27-G27)) -> 35 | I27: SUSPENSÃO, CAMBIO | J27: 45884 | K27: CONTRATAÇÃO - DESCARGA
A28: 16224 | B28: CMW7420 | C28: 2010 | D28: VECTRA | E28: COPOM | F28: 15-161 | G28: 45855 | H28: =IF(G28="","",IF(J28="",TODAY()-G28,J28-G28)) -> 29 | I28: SISTEMA ELETRICO/MOTOR/SUSPENSÃO | J28: 45884 | K28: CONTRATAÇÃO - DESCARGA
... A30: 16010 | B30: FDB4938 | C30: 2018 | D30: SPIN | E30: SAF | F30: 17-16 | G30: 45820 | H30: =IF(G30="","",IF(J30="",TODAY()-G30,J30-G30)) -> 64 | I30: ELÉTRICO/ MOTOR | J30: 45884 | K30: CONTRATAÇÃO - DESCARGA
A31: 16011 | B31: BYZ7654 | C31: 2018 | D31: SPIN | E31: SAF | F31: 45947 | G31: 45820 | H31: =IF(G31="","",IF(J31="",TODAY()-G31,J31-G31)) -> 64 | I31: REVISAO GERAL | J31: 45884 | K31: CONTRATAÇÃO - DESCARGA
A32: 16653 | B32: FPZ5988 | C32: 2018 | D32: PALIO W | E32: SAF | F32: 22-93 | G32: 45923 | H32: =IF(G32="","",IF(J32="",TODAY()-G32,J32-G32)) -> 57 | I32: VIATURA COM SUPERAQUECIMENTO/ AVALIAÇÃO PARA DESCARGA | J32: 45980 | K32: CONTRATAÇÃO - DESCARGA
A33: 16812 | B33: GAV2510 | C33: 2015 | D33: SPIN | E33: CMED | F33: 22-750 | G33: 45945 | H33: =IF(G33="","",IF(J33="",TODAY()-G33,J33-G33)) -> 40 | I33: DESCARGA | J33: 45985 | K33: CONTRATAÇÃO - DESCARGA
A34: 16676 | B34: FAT4978 | C34: 2015 | D34: SPIN | E34: DTIC | F34: 22-741 | G34: 45925 | H34: =IF(G34="","",IF(J34="",TODAY()-G34,J34-G34)) -> 60 | I34: DESCARGA | J34: 45985 | K34: CONTRATAÇÃO - DESCARGA
A35: 16667 | B35: DJL7764 | C35: 2010 | D35: BLAZER | E35: DSACG | F35: 15-92 | G35: 45925 | H35: =IF(G35="","",IF(J35="",TODAY()-G35,J35-G35)) -> 300 | I35: AVALIAÇÃO PARA POSSÍVEL DESCARGA | K35: CONTRATAÇÃO - DESCARGA
A36: 16676 | B36: FAT4978 | C36: 2015 | D36: SPIN | E36: DTIC | F36: 22-741 | G36: 45925 | H36: =IF(G36="","",IF(J36="",TODAY()-G36,J36-G36)) -> 300 | I36: PORTA DO MOTORISTA NÃO ABRE POR DENTRO, FALHA NO MOTOR, PNEU TRASEIRO FURADO | K36: CONTRATAÇÃO - DESCARGA
A37: 16784 | B37: GBK4005 | C37: 2015 | D37: SPIN | E37: CMM | F37: 22-684 | G37: 45940 | H37: =IF(G37="","",IF(J37="",TODAY()-G37,J37-G37)) -> 285 | I37: ARREFECIMENTO/ VIATURA NÃO LIGA POSSÍVEL BATERIA | K37: CONTRATAÇÃO - DESCARGA
A38: 16812 | B38: GAV2510 | C38: 2015 | D38: SPIN | E38: CMED | F38: 22-750 | G38: 45945 | H38: =IF(G38="","",IF(J38="",TODAY()-G38,J38-G38)) -> 280 | I38: FREIO; SUSPENSÃO ; DIREÇÃO; | K38: CONTRATAÇÃO - DESCARGA
A39: 16787 | B39: EEF8713 | C39: 2014 | D39: COROLLA | E39: SAF | F39: 15-14 | G39: 45943 | H39: =IF(G39="","",IF(J39="",TODAY()-G39,J39-G39)) -> 282 | I39: REVISÃO GERAL (POSSIVEL DESCARGA) | K39: CONTRATAÇÃO - DESCARGA
A40: 16790 | B40: DJL7766 | C40: 2011 | D40: BLAZER | E40: DTIC | F40: 15-93 | G40: 45943 | H40: =IF(G40="","",IF(J40="",TODAY()-G40,J40-G40)) -> 282 | I40: REVISÃO GERAL | K40: CONTRATAÇÃO - DESCARGA
A41: 16812 | B41: GAV2510 | C41: 2015 | D41: SPIN | E41: CMED | F41: 22-750 | G41: 45945 | H41: =IF(G41="","",IF(J41="",TODAY()-G41,J41-G41)) -> 280 | I41: REVISÃO SUSPENSÃO, FREIOS, PNEUS, ALINHAMENTO E BALANCEAMENTO. | K41: CONTRATAÇÃO - DESCARGA
A42: 16892 | B42: GBT1863 | C42: 2015 | D42: SPIN | E42: CPC | F42: 22-84 | G42: 45958 | H42: =IF(G42="","",IF(J42="",TODAY()-G42,J42-G42)) -> 267 | I42: INJEÇÃO ELETRÔNICA (MOTOR RAJANDO, BATENDO VÁLVULAS) | K42: CONTRATAÇÃO - DESCARGA
A43: 16981 | B43: GBK3310 | C43: 2015 | D43: SPIN | E43: CPC | F43: 22-92 | G43: 45978 | H43: =IF(G43="","",IF(J43="",TODAY()-G43,J43-G43)) -> 247 | I43: VTR FALHANDOBATENDO MOTOR, VAZANDO AGUA | K43: CONTRATAÇÃO - DESCARGA
A44: 17099 | B44: DJM8726 | C44: 2014 | D44: FIORINO | E44: CIPM | F44: 8-318 | G44: 46000 | H44: =IF(G44="","",IF(J44="",TODAY()-G44,J44-G44)) -> 225 | I44: MOTOR | K44: CONTRATAÇÃO - DESCARGA
A45: 17097 | B45: CMW7377 | C45: 2011 | D45: VECTRA | E45: CRPM | F45: 15-139 | G45: 46000 | H45: =IF(G45="","",IF(J45="",TODAY()-G45,J45-G45)) -> 225 | I45: MOTOR, SUSPENSAO | K45: CONTRATAÇÃO - DESCARGA
A46: 17061 | B46: CMW7410 | C46: 2010 | D46: VECTRA | E46: DSA/CG ( ECE-SAF) | F46: 15-157 | G46: 45994 | H46: =IF(G46="","",IF(J46="",TODAY()-G46,J46-G46)) -> 231 | I46: DESCARGA | K46: CONTRATAÇÃO - DESCARGA
A47: 17302 | B47: CMW8260 | C47: 2010 | D47: VECTRA | E47: CMM/SAF | F47: 15-194 | G47: 46044 | H47: =IF(G47="","",IF(J47="",TODAY()-G47,J47-G47)) -> 181 | I47: MOTOR / SUSPENSÃO | K47: CONTRATAÇÃO - DESCARGA

Sheet VTR PRONTA
A1: O.S. | B1: PLACA | C1: ANO | D1: MARCA/MODELO | E1: UNIDADE | F1: Prefixo | G1: DATA DE ENTRADA NA LINHA | H1: TEMPO PARADA | I1: PROBLEMA RELATADO | J1: DATA DE SAÍDA | K1: DESTINO
A2: 0 | B2: STT7I41 | C2: 2023 | D2: COROLLA | E2: 05 BPMM | F2: M-05365 | G2: 45625 | H2: =IF(G2="","",IF(J2="",TODAY()-G2,J2-G2)) -> 0 | I2: APOIO OPERAÇÃO VERÃO TROCA DE PNEU DIANTEIRO DIREITO | J2: 45625 | K2: REPARADO - LIBERADA
A3: 0 | B3: SVO9C79 | C3: 2023 | D3: COROLLA | E3: 05 BPMM | F3: M-05371 | G3: 45625 | H3: =IF(G3="","",IF(J3="",TODAY()-G3,J3-G3)) -> 0 | I3: APOIO OPERAÇÃO VERÃO TROCA DE PNEU DIANTEIRO ESQUERDO | J3: 45625 | K3: REPARADO - LIBERADA
A4: 0 | B4: ECO5J34 | C4: 2022 | D4: TRAILBLAZER | E4: BAEP | F4: E-07218 | G4: 45660 | H4: =IF(G4="","",IF(J4="",TODAY()-G4,J4-G4)) -> 0 | I4: VISTORIA PARA OPERAÇÃO VERÃO/ | J4: 45660 | K4: CONTRATAÇÃO
A5: 0 | B5: FSB7D43 | C5: 2020 | D5: TRAILBLEZER | E5: BAEP | F5: E-07111 | G5: 45660 | H5: =IF(G5="","",IF(J5="",TODAY()-G5,J5-G5)) -> 0 | I5: VISTORIA PARA OPERAÇÃO VERÃO/ REPROVADA; PNEUS DIANEIROS E TRASEIROS E TROCA DE ÓLEO | J5: 45660 | K5: REPARADO - LIBERADA
A6: 0 | B6: DII9749 | C6: 2019 | D6: SPIN | E6: 5BPM/M | F6: 5337 | G6: 45775 | H6: =IF(G6="","",IF(J6="",TODAY()-G6,J6-G6)) -> 0 | I6: VISTORIA DE RECOLHA (REPROVADA) | J6: 45775 | K6: REPARADO - LIBERADA
A7: 0 | B7: DSR8379 | C7: 2019 | D7: SPIN | E7: 5ºBPM/M | F7: M-05339 | G7: 45775 | H7: =IF(G7="","",IF(J7="",TODAY()-G7,J7-G7)) -> 0 | I7: VISTORIA DE RECOLHA - APROVADA | J7: 45775 | K7: REPARADO - LIBERADA
A8: 0 | B8: BSX7I45 | C8: 2019 | D8: DUSTER | E8: 9BPM/M | F8: 9219 | G8: 45775 | H8: =IF(G8="","",IF(J8="",TODAY()-G8,J8-G8)) -> 0 | I8: REAVALIAÇÃO DE RECOLHA (APROVADA) | J8: 45775 | K8: REPARADO - LIBERADA
A9: 6276 | B9: DJM8798 | C9: 2013 | D9: HILUX | E9: EEF | F9: 3-523 | G9: 45523 | H9: =IF(G9="","",IF(J9="",TODAY()-G9,J9-G9)) -> 1 | I9: ROLAMENTO REY CARDAN | J9: 45524 | K9: CONTRATAÇÃO
A10: 7818 | B10: EEF9171 | C10: 2014 | D10: SPACEFOX | E10: APMBB | F10: BA-040 | G10: 45041 | H10: =IF(G10="","",IF(J10="",TODAY()-G10,J10-G10)) -> 615 | I10: TROCA DE BATERIA | J10: 45656 | K10: REPARADO - LIBERADA
A11: 9737 | B11: EEF9384 | C11: 2014 | D11: HILUX | E11: CMM/SAF | F11: ***** | G11: 45566 | H11: =IF(G11="","",IF(J11="",TODAY()-G11,J11-G11)) -> 1 | I11: TROCA DOS CILINDROS DO FREIO TRASEIRO (CARTÃO DE ADIANTAMENTO) | J11: 45567 | K11: SINALIZADOR
A12: 10235 | B12: ETE-0383 | C12: 2018 | D12: TRAILBLAZER | E12: CPM | F12: 3-529 | G12: 45492 | H12: =IF(G12="","",IF(J12="",TODAY()-G12,J12-G12)) -> 0 | I12: TROCA LÂMPADA FAROL DE POSIÇÃO | J12: 45492 | K12: REPARADO - LIBERADA
A13: 11132 | B13: FWI1421 | C13: 2015 | D13: SPIN | E13: ESSGT | F13: ESSGT 0-20 | G13: 45562 | H13: =IF(G13="","",IF(J13="",TODAY()-G13,J13-G13)) -> 3 | I13: TROCA DE BATERIA | J13: 45565 | K13: REPARADO - LIBERADA
A14: 11449 | B14: DJM8683 | C14: 2014 | D14: CRUZE | E14: DEC | F14: 15-109 | G14: 45338 | H14: =IF(G14="","",IF(J14="",TODAY()-G14,J14-G14)) -> 123 | I14: QUEIMANDO ÓLEO | J14: 45461 | K14: REPARADO - LIBERADA
A15: 11744 | B15: FCF9549 | C15: 2017 | D15: PALIO WEEKEND | E15: CIAP | F15: 22-1308 | G15: 45356 | H15: =IF(G15="","",IF(J15="",TODAY()-G15,J15-G15)) -> 105 | I15: BATERIA NÃO SEGURA CARGA | J15: 45461 | K15: GRAFISMO
A16: 11838 | B16: GBA9890 | C16: 2015 | D16: SPIN | E16: CMM | F16: 22-836 | G16: 45359 | H16: =IF(G16="","",IF(J16="",TODAY()-G16,J16-G16)) -> 97 | I16: MOTOR / SUSPENSÃO/ AR CONDICIONADO | J16: 45456 | K16: CONTRATAÇÃO
A17: 11877 | B17: GBA6310 | C17: 2015 | D17: SPIN | E17: APMBB | F17: BA-046 | G17: 45362 | H17: =IF(G17="","",IF(J17="",TODAY()-G17,J17-G17)) -> 102 | I17: SUSPENSÃO TRAS. E DIANT/ INJEÇÃO ELETR./ PNEUS/ LANTERNAS | J17: 45464 | K17: CONTRATAÇÃO
A18: 11892 | B18: GBQ4440 | C18: 2015 | D18: SPIN | E18: CMM | F18: 22-464 | G18: 45363 | H18: =IF(G18="","",IF(J18="",TODAY()-G18,J18-G18)) -> 106 | I18: AR CONDICIONADO/ ARREFECIMENTO/BARULHO MOTOR | J18: 45469 | K18: CONTRATAÇÃO
A19: 11898 | B19: FVU3593 | C19: 2015 | D19: SPIN | E19: APMTJ | F19: 17-13 | G19: 45363 | H19: =IF(G19="","",IF(J19="",TODAY()-G19,J19-G19)) -> 101 | I19: VAZAMENTO ÓLEO MOTOR/ SINALIZADOR | J19: 45464 | K19: CONTRATAÇÃO
A20: 12104 | B20: CMW7395 | C20: 2011 | D20: VECTRA | E20: COORDOP PM | F20: 15-134 | G20: 45476 | H20: =IF(G20="","",IF(J20="",TODAY()-G20,J20-G20)) -> 0 | I20: TROCA DE BATERIA | J20: 45476 | K20: REPARADO - LIBERADA
... A39: 12968 | B39: FPP1023 | C39: 2019 | D39: TRAILBLAZER | E39: COPOM | F39: 3-826 | G39: 45449 | H39: =IF(G39="","",IF(J39="",TODAY()-G39,J39-G39)) -> 4 | I39: AR CONDICIONADO INOPERANE | J39: 45453 | K39: CONTRATAÇÃO
A40: 12981 | B40: GDN4E65 | C40: 2021 | D40: TRAILBLAZER | E40: PMRG | F40: 45308 | G40: 45453 | H40: =IF(G40="","",IF(J40="",TODAY()-G40,J40-G40)) -> 0 | I40: TROCA DE PASTILHA DE FREIO | J40: 45453 | K40: GRAFISMO
A41: 12982 | B41: ETZ7163 | C41: 2020 | D41: SPIN | E41: PMRG | F41: 15-20 | G41: 45450 | H41: =IF(G41="","",IF(J41="",TODAY()-G41,J41-G41)) -> 3 | I41: MOTOR DE ARRANQUE | J41: 45453 | K41: CONTRATAÇÃO
A42: 12985 | B42: BYP4277 | C42: 2018 | D42: SPIN | E42: APMBB | F42: BA-050 | G42: 45525 | H42: =IF(G42="","",IF(J42="",TODAY()-G42,J42-G42)) -> 2 | I42: REPARO NO CHICOTE DO FAROL E TROCA DE LÂMPADAS | J42: 23/08/2024 | K42: GRAFISMO
A43: 12986 | B43: DJL7764 | C43: 2011 | D43: BLAZER | E43: DSA/CG | F43: 15-92 | G43: 45450 | H43: =IF(G43="","",IF(J43="",TODAY()-G43,J43-G43)) -> 5 | I43: REPARO CHAVE DE IGNIÇÃO | J43: 45455 | K43: REPARADO - LIBERADA
A44: 12994 | B44: GAD6947 | C44: 2020 | D44: FIAT UNO WAY | E44: CIAP | F44: 45427 | G44: 45453 | H44: =IF(G44="","",IF(J44="",TODAY()-G44,J44-G44)) -> 0 | I44: PASTILHA DE FREIO | J44: 45453 | K44: REPARADO - LIBERADA
A45: 12996 | B45: CFY4296 | C45: 2014 | D45: SPACE FOX | E45: APMBB | F45: BA-023 | G45: 45453 | H45: =IF(G45="","",IF(J45="",TODAY()-G45,J45-G45)) -> 66 | I45: ARREFECIMENTO/ INJEÇÃO/ BALANCIAMENTO | J45: 45519 | K45: CONTRATAÇÃO
A46: 12997 | B46: DZF0F31 | C46: 2021 | D46: DUSTER | E46: CMIL | F46: 22-196 | G46: 45456 | H46: =IF(G46="","",IF(J46="",TODAY()-G46,J46-G46)) -> 0 | I46: REVISÃO ELETRICA | J46: 45456 | K46: REPARADO - LIBERADA
A47: 13000 | B47: GCG1620 | C47: 2015 | D47: SPIN | E47: CPC | F47: 22-835 | G47: 45454 | H47: =IF(G47="","",IF(J47="",TODAY()-G47,J47-G47)) -> 10 | I47: FALHA DE IGNIÇÃO/ TROCA DE ÓLEO | J47: 45464 | K47: REPARADO - LIBERADA
A48: 13004 | B48: FYR7284 | C48: 2015 | D48: GOL CITY | E48: CIPM | F48: 8-787 | G48: 45454 | H48: =IF(G48="","",IF(J48="",TODAY()-G48,J48-G48)) -> 0 | I48: PARABRISA TRINCADO | J48: 45454 | K48: CONTRATAÇÃO
A49: 13005 | B49: FQW6145 | C49: 2015 | D49: CRUZE | E49: CIPM | F49: 8-851 | G49: 45454 | H49: =IF(G49="","",IF(J49="",TODAY()-G49,J49-G49)) -> 2 | I49: MOTOR/ AR COND./ SUSPENSÃO | J49: 45456 | K49: CONTRATAÇÃO
A50: 13006 | B50: GAS3139 | C50: 2016 | D50: SPIN | E50: 3ºEM/PM | F50: 15-17 | G50: 45455 | H50: =IF(G50="","",IF(J50="",TODAY()-G50,J50-G50)) -> 40 | I50: REVISÃO GERAL | J50: 45495 | K50: REPARADO - LIBERADA
A51: 13009 | B51: FYL5201 | C51: 2015 | D51: MONTANA | E51: CIPM | F51: 8-876 | G51: 45454 | H51: =IF(G51="","",IF(J51="",TODAY()-G51,J51-G51)) -> 0 | I51: TROCA DE LAMPADAS | J51: 45454 | K51: CONTRATAÇÃO
A52: 13011 | B52: FNR2582 | C52: 2015 | D52: TRAILBLAZER | E52: CMM | F52: 3-210 | G52: 45454 | H52: =IF(G52="","",IF(J52="",TODAY()-G52,J52-G52)) -> 0 | I52: TROCA DE LAMPADA/ ANÁLISE COM SCANNER | J52: 45454 | K52: BORRACHARIA
A53: 13017 | B53: EEF8697 | C53: 2014 | D53: S10 | E53: DSA/CG | F53: 3-276 | G53: 45455 | H53: =IF(G53="","",IF(J53="",TODAY()-G53,J53-G53)) -> 1 | I53: REVISÃO GERAL | J53: 45456 | K53: BORRACHARIA
A54: 13033 | B54: EEF8703 | C54: 2015 | D54: COROLLA | E54: GAB COM GERAL | F54: 1-120 | G54: 45456 | H54: =IF(G54="","",IF(J54="",TODAY()-G54,J54-G54)) -> 0 | I54: PARABARRO | J54: 45456 | K54: CONTRATAÇÃO
A55: 13035 | B55: REV4E91 | C55: 2022 | D55: S10 | E55: DTIC | F55: 15-49 | G55: 45723 | H55: =IF(G55="","",IF(J55="",TODAY()-G55,J55-G55)) -> 3 | I55: AJUSTE NO ESTRIBO, TROCA DE ÓLEO | J55: 45726 | K55: REPARADO - LIBERADA
A56: 13047 | B56: CMW7420 | C56: 2011 | D56: VECTRA | E56: COPOM | F56: 15-161 | G56: 45457 | H56: =IF(G56="","",IF(J56="",TODAY()-G56,J56-G56)) -> 17 | I56: TROCA DE PASTILHA DE FREIO/ FAROL QUEBRADO | J56: 45474 | K56: REPARADO - LIBERADA
... A65: 13073 | B65: EZU7632 | C65: 2019 | D65: HILUX SW4 | E65: SSP | F65: 15-33 | G65: 45461 | H65: =IF(G65="","",IF(J65="",TODAY()-G65,J65-G65)) -> 0 | I65: LAMPADA FAROL | J65: 45461 | K65: REPARADO - LIBERADA
A66: 13074 | B66: FDB8J91 | C66: 2022 | D66: TRAILBLAZER | E66: PMRG | F66: 45368 | G66: 45461 | H66: =IF(G66="","",IF(J66="",TODAY()-G66,J66-G66)) -> 0 | I66: TROCA DE BATERIA | J66: 45461 | K66: REPARADO - LIBERADA
A67: 13079 | B67: EEF9604 | C67: 2014 | D67: COROLLA | E67: GAB CMDO GERAL | F67: 1-166 | G67: 45461 | H67: =IF(G67="","",IF(J67="",TODAY()-G67,J67-G67)) -> 0 | I67: TROCA DE BATERIA | J67: 45461 | K67: REPARADO - LIBERADA
A68: 13093 | B68: DKK4127 | C68: 2018 | D68: SPIN | E68: DL | F68: 22-121 | G68: 45464 | H68: =IF(G68="","",IF(J68="",TODAY()-G68,J68-G68)) -> 0 | I68: TROCA DE BATERIA | J68: 45464 | K68: REPARADO - LIBERADA
A69: 13100 | B69: CFY2788 | C69: 2014 | D69: DUSTER | E69: SAF | F69: 22-468 | G69: 45463 | H69: =IF(G69="","",IF(J69="",TODAY()-G69,J69-G69)) -> 46 | I69: PARTE ELÉTRICA E ARREFECIMENTO | J69: 45509 | K69: REPARADO - LIBERADA
A70: 13106 | B70: EOA8957 | C70: 2019 | D70: TRAILBLAZER | E70: PMRG | F70: 17-225 | G70: 45463 | H70: =IF(G70="","",IF(J70="",TODAY()-G70,J70-G70)) -> 1 | I70: PASTILHA DE FREIO / DISCO DE FREIO/ | J70: 45464 | K70: REPARADO - LIBERADA
A71: 13114 | B71: FOZ9B35 | C71: 2022 | D71: TRAILBLAZER | E71: CAVPM | F71: 3-96 | G71: 45464 | H71: =IF(G71="","",IF(J71="",TODAY()-G71,J71-G71)) -> 0 | I71: TROCA DO PARABRISA | J71: 45464 | K71: CONTRATAÇÃO
A72: 13115 | B72: EEF8814 | C72: 2014 | D72: COROLLA | E72: DTIC | F72: 1-131 | G72: 45464 | H72: =IF(G72="","",IF(J72="",TODAY()-G72,J72-G72)) -> 0 | I72: BOMBA DE COMBUSTÍVEL | J72: 45464 | K72: CONTRATAÇÃO
A73: 13116 | B73: CUJ8C35 | C73: 2022 | D73: DUSTER | E73: APMBB | F73: BA-083 | G73: 45464 | H73: =IF(G73="","",IF(J73="",TODAY()-G73,J73-G73)) -> 0 | I73: TROCA DE BATERIA ( start stop) VTR RODANDO | J73: 45464 | K73: CONTRATAÇÃO
A74: 13117 | B74: GEM9466 | C74: 2018 | D74: SPIN | E74: APMPGJ | F74: 22-272 | G74: 45464 | H74: =IF(G74="","",IF(J74="",TODAY()-G74,J74-G74)) -> 74 | I74: VTR FALHANDO | J74: 45538 | K74: CONTRATAÇÃO
A75: 13121 | B75: GAD4055 | C75: 2015 | D75: SPIN | E75: C MUS | F75: 22-1301 | G75: 45467 | H75: =IF(G75="","",IF(J75="",TODAY()-G75,J75-G75)) -> 3 | I75: MAQUINA VIDRO DIANT DIR ( reparado ) | J75: 45470 | K75: REPARADO - LIBERADA
A76: 13126 | B76: FNW5G94 | C76: 2022 | D76: TRAILBLAZER | E76: APMSSP | F76: 1-67 | G76: 45467 | H76: =IF(G76="","",IF(J76="",TODAY()-G76,J76-G76)) -> 0 | I76: TROCA DOS FLUÍDOS | J76: 45467 | K76: CONTRATAÇÃO
A77: 13129 | B77: FZV0B15 | C77: 2022 | D77: CRUZE | E77: ESSGT | F77: 15-94 | G77: 45467 | H77: =IF(G77="","",IF(J77="",TODAY()-G77,J77-G77)) -> 0 | I77: LAMPADA DE FREIO | J77: 45467 | K77: REPARADO - LIBERADA
A78: 13134 | B78: FWP4A94 | C78: 2022 | D78: TRAILBLAZER | E78: APMCMSP | F78: 15-207 | G78: 45467 | H78: =IF(G78="","",IF(J78="",TODAY()-G78,J78-G78)) -> 0 | I78: PASTILHADE FREIO | J78: 45467 | K78: REPARADO - LIBERADA
... A82: 13151 | B82: GHH6B47 | C82: 2022 | D82: TRAILBLAZER | E82: SAF | F82: 1-35 | G82: 45469 | H82: =IF(G82="","",IF(J82="",TODAY()-G82,J82-G82)) -> 1 | I82: REAPERTO DA SUSPENSÃO | J82: 45470 | K82: REPARADO - LIBERADA
A83: 13152 | B83: GIT2F28 | C83: 2022 | D83: TRAILBLAZER | E83: PMRG | F83: 45339 | G83: 45468 | H83: =IF(G83="","",IF(J83="",TODAY()-G83,J83-G83)) -> 38 | I83: BATERIA/ FREIO/ SINALIZADOR | J83: 45506 | K83: SINALIZADOR
A84: 13160 | B84: DZF0F31 | C84: 2022 | D84: DUSTER | E84: C MIL | F84: 22-196 | G84: 45469 | H84: =IF(G84="","",IF(J84="",TODAY()-G84,J84-G84)) -> 16 | I84: VENTOINHA NÃO FUNCIONA | J84: 45485 | K84: REPARADO - LIBERADA
A85: 13161 | B85: EVD0F41 | C85: 2022 | D85: TRAILBLAZER | E85: CPRV | F85: 1-50 | G85: 45469 | H85: =IF(G85="","",IF(J85="",TODAY()-G85,J85-G85)) -> 0 | I85: TROCA 04 PNEUS | J85: 45469 | K85: REPARADO - LIBERADA
A86: 13168 | B86: FJQ9E35 | C86: 2022 | D86: TRAILBLAZER | E86: CIPM | F86: 3-1026 | G86: 45470 | H86: =IF(G86="","",IF(J86="",TODAY()-G86,J86-G86)) -> 0 | I86: TROCA DE LÂMPADA | J86: 45470 | K86: REPARADO - LIBERADA
A87: 13173 | B87: EYN7B54 | C87: 2022 | D87: CRUZE | E87: CIPM | F87: 8-411 | G87: 45470 | H87: =IF(G87="","",IF(J87="",TODAY()-G87,J87-G87)) -> 0 | I87: TROCA DE LAMPADAS DE FREIO | J87: 45470 | K87: REPARADO - LIBERADA
A88: 13184 | B88: CFY5701 | C88: 2013 | D88: HILUX | E88: CMM | F88: 15-293 | G88: 45471 | H88: =IF(G88="","",IF(J88="",TODAY()-G88,J88-G88)) -> 74 | I88: DESCARACTERIZAÇÃO ( GRUPO 3 PARA 15) | J88: 45545 | K88: CONTRATAÇÃO
A89: 13186 | B89: EOC5512 | C89: 2018 | D89: SPIN | E89: 33ºBPM/I | F89: 22-1143 | G89: 45471 | H89: =IF(G89="","",IF(J89="",TODAY()-G89,J89-G89)) -> 0 | I89: REPARO NO ARREFECIMENTO ( APOIO EMERGENCIAL ) | J89: 45471 | K89: REPARADO - LIBERADA
A90: 13192 | B90: REV4E94 | C90: 2022 | D90: S10 | E90: CMB | F90: 15-47 | G90: 45474 | H90: =IF(G90="","",IF(J90="",TODAY()-G90,J90-G90)) -> 0 | I90: TROCA DE ÓLEO DO MOTOR E FILTRO | J90: 45474 | K90: REPARADO - LIBERADA
A91: 13196 | B91: GAG2E24 | C91: 2022 | D91: MOBI | E91: CPM | F91: 8-1066 | G91: 45474 | H91: =IF(G91="","",IF(J91="",TODAY()-G91,J91-G91)) -> 0 | I91: TROCA DA BATERIA | J91: 45474 | K91: REPARADO - LIBERADA
A92: 13199 | B92: FOK4089 | C92: 2015 | D92: SPIN | E92: CPC | F92: 22-802 | G92: 45474 | H92: =IF(G92="","",IF(J92="",TODAY()-G92,J92-G92)) -> 57 | I92: FALHA DE IGNIÇÃO | J92: 45531 | K92: CONTRATAÇÃO
A93: 13201 | B93: FAT4978 | C93: 2015 | D93: SPIN | E93: DTIC | F93: 22-741 | G93: 45477 | H93: =IF(G93="","",IF(J93="",TODAY()-G93,J93-G93)) -> 0 | I93: TROCA DA BATERIA/ REVISÃO ELÉTRICA | J93: 45477 | K93: GRAFISMO
A94: 13208 | B94: DCF7791 | C94: 2020 | D94: SPIN | E94: CMM | F94: 0 | G94: 45495 | H94: =IF(G94="","",IF(J94="",TODAY()-G94,J94-G94)) -> 28 | I94: DESCARACTERIZAR ( GRUPO 22 PARA GRUPO 15 ) | J94: 45523 | K94: CONTRATAÇÃO
A95: 13208 | B95: DCF7791 | C95: 2019 | D95: SPIN | E95: SAF | F95: SEM PREF. | G95: 45590 | H95: =IF(G95="","",IF(J95="",TODAY()-G95,J95-G95)) -> 0 | I95: TROCADO BATERIA (NOVA) | J95: 45590 | K95: REPARADO - LIBERADA
A96: 13209 | B96: FWS9C43 | C96: 2018 | D96: SPIN | E96: CMM | F96: 0 | G96: 45495 | H96: =IF(G96="","",IF(J96="",TODAY()-G96,J96-G96)) -> 28 | I96: DESCARACTERIZAR ( GRUPO 22 PARA GRUPO 15 ) | J96: 45523 | K96: CONTRATAÇÃO
A97: 13209 | B97: FWS9C43 | C97: 2018 | D97: SPIN | E97: CMM | F97: 0 | G97: 45495 | H97: =IF(G97="","",IF(J97="",TODAY()-G97,J97-G97)) -> 32 | I97: DESCARACTERIZAR ( GRUPO 22 PARA GRUPO 15 ) | J97: 45527 | K97: CONTRATAÇÃO
A98: 13210 | B98: DVK8649 | C98: 2020 | D98: DUSTER | E98: CMM | F98: 0 | G98: 45495 | H98: =IF(G98="","",IF(J98="",TODAY()-G98,J98-G98)) -> 32 | I98: DESCARACTERIZAR ( GRUPO 22 PARA GRUPO 15 ) | J98: 45527 | K98: CONTRATAÇÃO
A99: 13211 | B99: FYU7586 | C99: 2019 | D99: DUSTER | E99: SAF | F99: 0 | G99: 45475 | H99: =IF(G99="","",IF(J99="",TODAY()-G99,J99-G99)) -> 59 | I99: DESCARACTERIZAÇÃO | J99: 45534 | K99: CONTRATAÇÃO
A100: 13211 | B100: FYU7586 | C100: 2020 | D100: DUSTER | E100: CMM | F100: 0 | G100: 45495 | H100: =IF(G100="","",IF(J100="",TODAY()-G100,J100-G100)) -> 32 | I100: DESCARACTERIZAR ( GRUPO 22 PARA GRUPO 15 ) | J100: 45527 | K100: CONTRATAÇÃO
A101: 13212 | B101: FMA0129 | C101: 2018 | D101: SPIN | E101: CMM | F101: 0 | G101: 45495 | H101: =IF(G101="","",IF(J101="",TODAY()-G101,J101-G101)) -> 32 | I101: DESCARACTERIZAR ( GRUPO 22 PARA GRUPO 15 ) | J101: 45527 | K101: CONTRATAÇÃO
A102: 13214 | B102: FPZ3H33 | C102: 2022 | D102: TRAILBLAZER | E102: APMAL | F102: 1-70 | G102: 45474 | H102: =IF(G102="","",IF(J102="",TODAY()-G102,J102-G102)) -> 0 | I102: TROCA DA LÂMPADA H27W/2 E LÂMPADA PINGO | J102: 45474 | K102: REPARADO - LIBERADA
A103: 13217 | B103: FNW5G94 | C103: 2022 | D103: TRAILBLAZER | E103: APMPMSP | F103: 1-67 | G103: 45475 | H103: =IF(G103="","",IF(J103="",TODAY()-G103,J103-G103)) -> 1 | I103: TROCA DE PNEUS/ CONTROLE DE ESTABILIDADE/ SUSPENSÃO | J103: 45476 | K103: CONTRATAÇÃO
A104: 13222 | B104: FDB4938 | C104: 2018 | D104: SPIN | E104: APMSSP | F104: 22-733 | G104: 45475 | H104: =IF(G104="","",IF(J104="",TODAY()-G104,J104-G104)) -> 0 | I104: TROCA DA BATERIA / TEST. DE MOTOR DE PARTIDA / TEST. ALTERNADOR | J104: 45475 | K104: REPARADO - LIBERADA
A105: 13224 | B105: EEF9249 | C105: 2014 | D105: SPACEFOX | E105: APMAL | F105: 45495 | G105: 45475 | H105: =IF(G105="","",IF(J105="",TODAY()-G105,J105-G105)) -> 0 | I105: TROCA DA BATERIA | J105: 45475 | K105: REPARADO - LIBERADA
A106: 13233 | B106: DJM9041 | C106: 2014 | D106: HILUX | E106: CMB | F106: 3-87 | G106: 45476 | H106: =IF(G106="","",IF(J106="",TODAY()-G106,J106-G106)) -> 0 | I106: TROCA DE ÓLEO E FILTROS | J106: 45476 | K106: REPARADO - LIBERADA
A107: 13235 | B107: FNA3823 | C107: 2018 | D107: SPIN | E107: COPOM | F107: 22-296 | G107: 45476 | H107: =IF(G107="","",IF(J107="",TODAY()-G107,J107-G107)) -> 64 | I107: PANE ELÉTRICA / MECANICA | J107: 45540 | K107: CONTRATAÇÃO
A108: 13237 | B108: EEF9604 | C108: 2015 | D108: COROLLA | E108: DTIC | F108: 1-166 | G108: 45476 | H108: =IF(G108="","",IF(J108="",TODAY()-G108,J108-G108)) -> 0 | I108: TROCA DE BATERIA AUXILIAR | J108: 45476 | K108: REPARADO - LIBERADA
A109: 13243 | B109: GIK1995 | C109: 2018 | D109: TRAILBLAZER | E109: DL | F109: 3-47 | G109: 45477 | H109: =IF(G109="","",IF(J109="",TODAY()-G109,J109-G109)) -> 6 | I109: TROCA DE PNEUA/ TROCA DE ÓLEO E FILTRO | J109: 45483 | K109: REPARADO - LIBERADA
A110: 13272 | B110: DIS6F91 | C110: 2022 | D110: TRAILBLAZER | E110: APMSSP | F110: 15-53 | G110: 45483 | H110: =IF(G110="","",IF(J110="",TODAY()-G110,J110-G110)) -> 0 | I110: TROCA DE ÓLEO E FILTROS | J110: 45483 | K110: REPARADO - LIBERADA
A111: 13273 | B111: GCJ2J25 | C111: 2022 | D111: TRAILBLAZER | E111: APMSSP | F111: 15-51 | G111: 45483 | H111: =IF(G111="","",IF(J111="",TODAY()-G111,J111-G111)) -> 0 | I111: PASTILHA DE FREIO TRASEIRO/ ÓLEO+FILTRO/ LÂMPADAS LEITURA VIA SCANNER | J111: 45483 | K111: REPARADO - LIBERADA
A112: 13278 | B112: EEF8698 | C112: 2014 | D112: S10 | E112: CMB | F112: 3-356 | G112: 45483 | H112: =IF(G112="","",IF(J112="",TODAY()-G112,J112-G112)) -> 0 | I112: TROCA DE ÓLEO E FILTROS | J112: 45483 | K112: REPARADO - LIBERADA
A113: 13279 | B113: BYY1563 | C113: 2022 | D113: SPIN | E113: APMBB | F113: BA-049 | G113: 45483 | H113: =IF(G113="","",IF(J113="",TODAY()-G113,J113-G113)) -> 54 | I113: EMBREAGEM | J113: 45537 | K113: CONTRATAÇÃO
A114: 13281 | B114: EEF9171 | C114: 2014 | D114: SPACEFOX | E114: APMBB | F114: BA-040 | G114: 45483 | H114: =IF(G114="","",IF(J114="",TODAY()-G114,J114-G114)) -> 63 | I114: MOTOR ( RESOLVIDO NA LINHA ) FREIO/ ( GARANTIA ) | J114: 45546 | K114: CONTRATAÇÃO
A115: 13283 | B115: EEF8703 | C115: 2014 | D115: COROLLA | E115: CMDO GERAL | F115: 1-120 | G115: 45483 | H115: =IF(G115="","",IF(J115="",TODAY()-G115,J115-G115)) -> 0 | I115: TROCA DE LAMPADA | J115: 45483 | K115: REPARADO - LIBERADA
A116: 13284 | B116: EEF8683 | C116: 2015 | D116: COROLLA | E116: CMM | F116: 1-113 | G116: 45483 | H116: =IF(G116="","",IF(J116="",TODAY()-G116,J116-G116)) -> 0 | I116: REVISÃO GERAL | J116: 45483 | K116: REPARADO - LIBERADA
A117: 13288 | B117: CDR1G22 | C117: 2022 | D117: DUSTER | E117: ESSGT | F117: ESSGT-032 | G117: 45483 | H117: =IF(G117="","",IF(J117="",TODAY()-G117,J117-G117)) -> 1 | I117: REVISÃO ELÉTRICA | J117: 45484 | K117: SINALIZADOR
... A131: 13331 | B131: CMW8260 | C131: 2011 | D131: VECTRA | E131: DPCDH | F131: 15-194 | G131: 45489 | H131: =IF(G131="","",IF(J131="",TODAY()-G131,J131-G131)) -> 0 | I131: LÂMPADA H7 ( FAROL BAIXO ) E REVISÃO SISTEMA ELÉTRICO ) | J131: 45489 | K131: REPARADO - LIBERADA
A132: 13332 | B132: CFY5853 | C132: 2013 | D132: HILUX | E132: ESSGT | F132: 1 | G132: 45489 | H132: =IF(G132="","",IF(J132="",TODAY()-G132,J132-G132)) -> 1 | I132: BATERIA/LÂMPADAS | J132: 45490 | K132: GRAFISMO
A133: 13333 | B133: FPP0162 | C133: 2019 | D133: SPIN | E133: ESSGT | F133: ESSGT-22 | G133: 45490 | H133: =IF(G133="","",IF(J133="",TODAY()-G133,J133-G133)) -> 5 | I133: REPARO NO MOTOR DE ARRANQUE | J133: 45495 | K133: REPARADO - LIBERADA
A134: 13336 | B134: EEF4153 | C134: 2009 | D134: ASTRA | E134: CCOMSOC | F134: 15-176 | G134: 45490 | H134: =IF(G134="","",IF(J134="",TODAY()-G134,J134-G134)) -> 27 | I134: TESTE DO SISTEMA ELÉTRICO | J134: 45517 | K134: REPARADO - LIBERADA
A135: 13337 | B135: FIP0147 | C135: 2022 | D135: TRAILBLAZER | E135: CIPM | F135: 1-49 | G135: 45490 | H135: =IF(G135="","",IF(J135="",TODAY()-G135,J135-G135)) -> 1 | I135: REVISÃO GERAL | J135: 45491 | K135: BORRACHARIA
A136: 13341 | B136: BYZ7654 | C136: 2018 | D136: SPIN | E136: APMTJ | F136: 45582 | G136: 45490 | H136: =IF(G136="","",IF(J136="",TODAY()-G136,J136-G136)) -> 0 | I136: REPARO EM 02 PNEUS ESTEPES TRAZIDOS DE VTR EM P.E. | J136: 45490 | K136: REPARADO - LIBERADA
A137: 13342 | B137: ETE0383 | C137: 2018 | D137: TRAILBLAZER | E137: CPM | F137: 3-529 | G137: 45490 | H137: =IF(G137="","",IF(J137="",TODAY()-G137,J137-G137)) -> 0 | I137: TROCA DE BATERIA | J137: 45490 | K137: REPARADO - LIBERADA
A138: 13345 | B138: FWR7D06 | C138: 2022 | D138: TRAILBLAZER | E138: DEC | F138: 1-88 | G138: 45490 | H138: =IF(G138="","",IF(J138="",TODAY()-G138,J138-G138)) -> 0 | I138: TROCA DE DISCO E PASTILHA DE FREIO TRASEIRO | J138: 45490 | K138: REPARADO - LIBERADA
A139: 13346 | B139: GFS6957 | C139: 2020 | D139: SPIN | E139: ESSGT | F139: ESSGT-029 | G139: 45495 | H139: =IF(G139="","",IF(J139="",TODAY()-G139,J139-G139)) -> 0 | I139: REAPERTO NO MOTOR DE ARRANQUE E TROCA DA PALHETA | J139: 45495 | K139: REPARADO - LIBERADA
A140: 13350 | B140: GCF3G15 | C140: 2022 | D140: TRAILBLAZER | E140: CMIL | F140: 15-73 | G140: 45490 | H140: =IF(G140="","",IF(J140="",TODAY()-G140,J140-G140)) -> 1 | I140: REMANEJAMENTO DO ESPELHO RETROVISOR LADO ESQUERDO | J140: 45491 | K140: REPARADO - LIBERADA
A141: 13353 | B141: DJM8728 | C141: 2014 | D141: FIORINO | E141: CIPM | F141: 8-334 | G141: 45491 | H141: =IF(G141="","",IF(J141="",TODAY()-G141,J141-G141)) -> 56 | I141: PNEUS, AVALIAÇAO MECANICA | J141: 45547 | K141: CONTRATAÇÃO
A142: 13356 | B142: GHH6B47 | C142: 2022 | D142: TRAILBLAZER | E142: CAJ | F142: 1-35 | G142: 45491 | H142: =IF(G142="","",IF(J142="",TODAY()-G142,J142-G142)) -> 0 | I142: TROCA DA LÂMPADA H27 E PINGÃO DA PLACA | J142: 45491 | K142: REPARADO - LIBERADA
...

Sheet ESTATISTICA
A1: QTD EM EXECUÇÃO | B1: PRAZO EM EXECUÇÃO (DIAS) | C1: QTD FINALIZADOS | D1: PRAZO FINALIZADOS (DIAS)
A2: =COUNT('VTR AGUARDANDO VISTORIA'!A:A)-A5 -> 482 | B2: =(SUMIF('VTR AGUARDANDO VISTORIA'!K:K,"<>CONTRATAÇÃO - DESCARGA",'VTR AGUARDANDO VISTORIA'!H:H))/A2 -> #VALUE! | C2: =COUNT('VTR PRONTA'!H:H) -> 1606 | D2: =(SUMIF('VTR PRONTA'!K:K,"<>CONTRATAÇÃO - DESCARGA",'VTR PRONTA'!H:H))/C2 -> 9.6899128
A4: QTD DESCARGA EXECUÇÃO | B4: PRAZO EXECUÇÃO DESCARGA (DIAS) | C4: QTD DESCARGA FINALIZADO | D4: PRAZO FINALIZADOS DESCARGA (DIAS)
A5: =COUNTIF('VTR AGUARDANDO VISTORIA'!K:K,"CONTRATAÇÃO - DESCARGA") -> 0 | B5: =IF(A5=0,0,(SUMIF('VTR AGUARDANDO VISTORIA'!K:K,"=CONTRATAÇÃO - DESCARGA",'VTR AGUARDANDO VISTORIA'!H:H))/A5) -> 0 | C5: =COUNT('VTR DESCARGA'!H:H) -> 46 | D5: =(SUMIF('VTR DESCARGA'!K:K,"=CONTRATAÇÃO - DESCARGA",'VTR DESCARGA'!H:H))/C5 -> 135.13043
